LICENSE
MANIFEST.in
README.rst
setup.py
django_translation_server.egg-info/PKG-INFO
django_translation_server.egg-info/SOURCES.txt
django_translation_server.egg-info/dependency_links.txt
django_translation_server.egg-info/requires.txt
django_translation_server.egg-info/top_level.txt
translation_server/__init__.py
translation_server/admin.py
translation_server/apps.py
translation_server/forms.py
translation_server/models.py
translation_server/serializers.py
translation_server/tests.py
translation_server/translation.py
translation_server/urls.py
translation_server/views.py
translation_server/management/__init__.py
translation_server/management/tests.py
translation_server/management/commands/__init__.py
translation_server/management/commands/make_translation.py
translation_server/management/commands/make_translation_migrations.py
translation_server/management/commands/translate.py
translation_server/management/commands/upload_csv.py
translation_server/migrations/0001_initial.py
translation_server/migrations/0002_auto_20161021_1254.py
translation_server/migrations/0003_auto_20161021_1303.py
translation_server/migrations/0004_auto_20170112_1833.py
translation_server/migrations/__init__.py
translation_server/static/admin/js/admin-translation-type.js
translation_server/static/admin/js/admin-translation.js